{
  "version": "5",
  "dialect": "mysql",
  "id": "23be506c-c3be-4b32-b3c7-c5b7bf2dbf15",
  "prevId": "fe165b1f-96e8-4872-aff8-e3cfe97a39c6",
  "tables": {
    "furniture": {
      "name": "furniture",
      "columns": {
        "id": {
          "name": "id",
          "type": "serial",
          "primaryKey": false,
          "notNull": true,
          "autoincrement": true
        },
        "userId": {
          "name": "userId",
          "type": "bigint unsigned",
          "primaryKey": false,
          "notNull": true,
          "autoincrement": false
        },
        "make": {
          "name": "make",
          "type": "varchar(255)",
          "primaryKey": false,
          "notNull": true,
          "autoincrement": false
        },
        "model": {
          "name": "model",
          "type": "varchar(255)",
          "primaryKey": false,
          "notNull": true,
          "autoincrement": false
        },
        "color": {
          "name": "color",
          "type": "varchar(255)",
          "primaryKey": false,
          "notNull": true,
          "autoincrement": false
        },
        "type": {
          "name": "type",
          "type": "varchar(255)",
          "primaryKey": false,
          "notNull": true,
          "autoincrement": false
        },
        "location": {
          "name": "location",
          "type": "varchar(255)",
          "primaryKey": false,
          "notNull": true,
          "autoincrement": false
        },
        "year": {
          "name": "year",
          "type": "varchar(255)",
          "primaryKey": false,
          "notNull": true,
          "autoincrement": false
        },
        "videoUrl": {
          "name": "videoUrl",
          "type": "varchar(255)",
          "primaryKey": false,
          "notNull": true,
          "autoincrement": false
        }
      },
      "indexes": {},
      "foreignKeys": {
        "furniture_userId_users_id_fk": {
          "name": "furniture_userId_users_id_fk",
          "tableFrom": "furniture",
          "tableTo": "users",
          "columnsFrom": [
            "userId"
          ],
          "columnsTo": [
            "id"
          ],
          "onDelete": "no action",
          "onUpdate": "no action"
        }
      },
      "compositePrimaryKeys": {
        "furniture_id": {
          "name": "furniture_id",
          "columns": [
            "id"
          ]
        }
      },
      "uniqueConstraints": {},
      "checkConstraint": {}
    },
    "images": {
      "name": "images",
      "columns": {
        "id": {
          "name": "id",
          "type": "serial",
          "primaryKey": false,
          "notNull": true,
          "autoincrement": true
        },
        "furnitureId": {
          "name": "furnitureId",
          "type": "bigint unsigned",
          "primaryKey": false,
          "notNull": true,
          "autoincrement": false
        },
        "imageUrl": {
          "name": "imageUrl",
          "type": "varchar(255)",
          "primaryKey": false,
          "notNull": true,
          "autoincrement": false
        }
      },
      "indexes": {},
      "foreignKeys": {
        "images_furnitureId_furniture_id_fk": {
          "name": "images_furnitureId_furniture_id_fk",
          "tableFrom": "images",
          "tableTo": "furniture",
          "columnsFrom": [
            "furnitureId"
          ],
          "columnsTo": [
            "id"
          ],
          "onDelete": "no action",
          "onUpdate": "no action"
        }
      },
      "compositePrimaryKeys": {
        "images_id": {
          "name": "images_id",
          "columns": [
            "id"
          ]
        }
      },
      "uniqueConstraints": {},
      "checkConstraint": {}
    },
    "users": {
      "name": "users",
      "columns": {
        "id": {
          "name": "id",
          "type": "serial",
          "primaryKey": false,
          "notNull": true,
          "autoincrement": true
        },
        "username": {
          "name": "username",
          "type": "varchar(255)",
          "primaryKey": false,
          "notNull": true,
          "autoincrement": false
        },
        "passwordHash": {
          "name": "passwordHash",
          "type": "varchar(255)",
          "primaryKey": false,
          "notNull": true,
          "autoincrement": false
        },
        "title": {
          "name": "title",
          "type": "varchar(255)",
          "primaryKey": false,
          "notNull": true,
          "autoincrement": false
        },
        "firstName": {
          "name": "firstName",
          "type": "varchar(255)",
          "primaryKey": false,
          "notNull": true,
          "autoincrement": false
        },
        "lastName": {
          "name": "lastName",
          "type": "varchar(255)",
          "primaryKey": false,
          "notNull": true,
          "autoincrement": false
        },
        "gender": {
          "name": "gender",
          "type": "varchar(255)",
          "primaryKey": false,
          "notNull": true,
          "autoincrement": false
        },
        "address1": {
          "name": "address1",
          "type": "varchar(255)",
          "primaryKey": false,
          "notNull": true,
          "autoincrement": false
        },
        "address2": {
          "name": "address2",
          "type": "varchar(255)",
          "primaryKey": false,
          "notNull": false,
          "autoincrement": false,
          "default": "''"
        },
        "address3": {
          "name": "address3",
          "type": "varchar(255)",
          "primaryKey": false,
          "notNull": false,
          "autoincrement": false,
          "default": "''"
        },
        "postcode": {
          "name": "postcode",
          "type": "varchar(255)",
          "primaryKey": false,
          "notNull": true,
          "autoincrement": false
        },
        "description": {
          "name": "description",
          "type": "varchar(255)",
          "primaryKey": false,
          "notNull": false,
          "autoincrement": false,
          "default": "''"
        },
        "email": {
          "name": "email",
          "type": "varchar(255)",
          "primaryKey": false,
          "notNull": true,
          "autoincrement": false
        },
        "telephone": {
          "name": "telephone",
          "type": "varchar(255)",
          "primaryKey": false,
          "notNull": true,
          "autoincrement": false
        },
        "profileImageUrl": {
          "name": "profileImageUrl",
          "type": "varchar(255)",
          "primaryKey": false,
          "notNull": true,
          "autoincrement": false
        }
      },
      "indexes": {},
      "foreignKeys": {},
      "compositePrimaryKeys": {
        "users_id": {
          "name": "users_id",
          "columns": [
            "id"
          ]
        }
      },
      "uniqueConstraints": {
        "users_username_unique": {
          "name": "users_username_unique",
          "columns": [
            "username"
          ]
        },
        "users_email_unique": {
          "name": "users_email_unique",
          "columns": [
            "email"
          ]
        }
      },
      "checkConstraint": {}
    }
  },
  "views": {},
  "_meta": {
    "schemas": {},
    "tables": {
      "\"furniture_details\"": "\"furniture\"",
      "\"documents\"": "\"images\""
    },
    "columns": {
      "\"images\".\"documentUrl\"": "\"images\".\"imageUrl\"",
      "\"furniture\".\"furnitureMake\"": "\"furniture\".\"make\"",
      "\"furniture\".\"furnitureModel\"": "\"furniture\".\"model\"",
      "\"furniture\".\"furnitureColor\"": "\"furniture\".\"color\"",
      "\"furniture\".\"furnitureType\"": "\"furniture\".\"type\"",
      "\"furniture\".\"videoId\"": "\"furniture\".\"videoUrl\"",
      "\"users\".\"profileImageId\"": "\"users\".\"profileImageUrl\""
    }
  },
  "internal": {
    "tables": {},
    "indexes": {}
  }
}